<?xml version="1.0" encoding="UTF-8"?>
<files psalm-version="3.14.2@3538fe1955d47f6ee926c0769d71af6db08aa488">
  <file src="Service/Calculator.php">
    <MixedArgument occurrences="4">
      <code>$populationCount</code>
      <code>$meanValue - $v</code>
      <code>$sum / ($populationCount - ($sample ? 1 : 0))</code>
      <code>$mean - $v</code>
    </MixedArgument>
    <MixedAssignment occurrences="4">
      <code>$v</code>
      <code>$zValues[]</code>
      <code>$v</code>
      <code>$v</code>
    </MixedAssignment>
    <MixedOperand occurrences="4">
      <code>$v</code>
      <code>$meanValue</code>
      <code>$populationCount</code>
      <code>$v</code>
    </MixedOperand>
  </file>
  <file src="Service/DistributionManager.php">
    <MixedArgument occurrences="4">
      <code>100 * $x / $population</code>
      <code>$summary</code>
      <code>$population</code>
      <code>$summary</code>
    </MixedArgument>
    <MixedArrayAccess occurrences="4">
      <code>$result[0]</code>
      <code>$result['population']</code>
      <code>$result[0]</code>
      <code>$result['population']</code>
    </MixedArrayAccess>
    <MixedAssignment occurrences="14">
      <code>$x0</code>
      <code>$y0</code>
      <code>$x1</code>
      <code>$y1</code>
      <code>$x</code>
      <code>$result</code>
      <code>$lowerFragment</code>
      <code>$population</code>
      <code>$result</code>
      <code>$upperFragment</code>
      <code>$population</code>
      <code>$summary</code>
      <code>$frequency</code>
      <code>$v</code>
    </MixedAssignment>
    <MixedInferredReturnType occurrences="1">
      <code>Summary</code>
    </MixedInferredReturnType>
    <MixedMethodCall occurrences="9">
      <code>getCumulativeFrequency</code>
      <code>getValue</code>
      <code>getCumulativeFrequency</code>
      <code>getValue</code>
      <code>getId</code>
      <code>setCumulativeFrequency</code>
      <code>setFrequency</code>
      <code>setValue</code>
      <code>setPopulation</code>
    </MixedMethodCall>
    <MixedOperand occurrences="8">
      <code>$x1</code>
      <code>$y0</code>
      <code>$y1</code>
      <code>($x1 - $x0) * ($value - $y0)</code>
      <code>$x0</code>
      <code>$x</code>
      <code>100 * $x</code>
      <code>$frequency</code>
    </MixedOperand>
    <MixedReturnStatement occurrences="1">
      <code>$summary</code>
    </MixedReturnStatement>
    <UndefinedInterfaceMethod occurrences="1">
      <code>findOneByName</code>
    </UndefinedInterfaceMethod>
  </file>
</files>
